<?xml version="1.0" encoding="UTF-8" standalone="yes"?>
<people total="46441" start="0" count="2">
  <person>
    <id>EcTIwdTfXk</id>
    <first-name>John</first-name>
    <last-name>Doe</last-name>
    <headline>Advertising</headline>
    <location>
      <name>Greater Seattle Area</name>
      <country>
        <code>us</code>
      </country>
    </location>
    <industry>Newspapers</industry>
    <connections total="224" />
    <num-recommenders>0</num-recommenders>
    <distance>1</distance>
    <positions total="2">
      <position>
        <id>44074500</id>
        <title>Advertising</title>
        <start-date>
          <year>2008</year>
          <month>5</month>
        </start-date>
        <is-current>true</is-current>
        <company>
          <name>The Times</name>
        </company>
      </position>
      <position>
        <id>2353376126</id>
        <title>Retail Advertising Manager</title>
        <start-date>
          <year>2004</year>
          <month>10</month>
        </start-date>
        <is-current>true</is-current>
        <company>
          <name>Herald-Republic</name>
        </company>
      </position>
    </positions>
    <api-standard-profile-request>
      <url>http://api.linkedin.com/v1/people/xxxxxx:full</url>
      <headers total="1">
        <http-header>
          <name>x-li-auth-token</name>
          <value>OUT_OF_NETWORK:0_t6</value>
        </http-header>
      </headers>
    </api-standard-profile-request>
    <site-standard-profile-request>
      <url>http://www.linkedin.com/profile?viewProfile=&amp;key=111140338&amp;authToken=0_t6&amp;authType=OUT_OF_NETWORK</url>
    </site-standard-profile-request>
  </person>
  <person>
    <id>xxxx</id>
    <first-name>Andy</first-name>
    <last-name>Hicks</last-name>
    <headline>Resident Manager</headline>
    <location>
      <name>Greater Seattle Area</name>
      <country>
        <code>us</code>
      </country>
    </location>
    <industry>Real Estate</industry>
    <connections total="26" />
    <num-recommenders>0</num-recommenders>
    <distance>1</distance>
    <positions total="1">
      <position>
        <id>23323423</id>
        <title>Resident Manager</title>
        <summary>Perform all duties of the Resident/Property Manager: Lease Administration, Rent Collection/Deposit, Respond to Tenant Requests, Site Maintenance, Marketing and Showing Apartments, Remodel and Tenant Improvement Oversight, Inventory Control/Purchasing, and General Upkeep of a Vintage Brick Apartment Building in West Seattle's Admiral District.</summary>
        <start-date>
          <year>2007</year>
          <month>4</month>
        </start-date>
        <is-current>true</is-current>
        <company>
          <name>The J Apartments</name>
        </company>
      </position>
    </positions>
    <api-standard-profile-request>
      <url>http://api.linkedin.com/v1/people/xxxxx:full</url>
      <headers total="1">
        <http-header>
          <name>x-li-auth-token</name>
          <value>OUT_OF_NETWORK:ATiX</value>
        </http-header>
      </headers>
    </api-standard-profile-request>
    <site-standard-profile-request>
      <url>http://www.linkedin.com/profile?viewProfile=&amp;key=11235833592&amp;authToken=ATiX&amp;authType=OUT_OF_NETWORK</url>
    </site-standard-profile-request>
  </person>
</people>
